mflib/README.md
mflib/__init__.py
mflib/core.py
mflib/data_transfer.py
mflib/mf_timestamp.py
mflib/mflib.py
mflib/mfvis.py
mflib/owl.py
mflib/owl_data.py
fabrictestbed_mflib-1.0.7.dist-info/licenses/LICENSE
fabrictestbed_mflib-1.0.7.dist-info/WHEEL
fabrictestbed_mflib-1.0.7.dist-info/METADATA
fabrictestbed_mflib-1.0.7.dist-info/RECORD
