Metadata-Version: 2.4
Name: fabrictestbed-mflib
Version: 1.0.7
Summary: FABRIC Measurement Framework Python Client Library - Makes monitoring FABRIC Slice easy.
Author: Song, Pinyi, Hussam
Author-email: Carpenter <csacarp0@g.uky.edu>
Requires-Python: >=3.9
Classifier: Programming Language :: Python :: 3
Classifier: License :: OSI Approved :: MIT License
Classifier: Operating System :: OS Independent
License-File: LICENSE
Project-URL: Homepage, https://github.com/fabric-testbed/mflib
